README.rst
setup.py
necrophos_wsgi/connection.py
necrophos_wsgi/event_loop.py
necrophos_wsgi/exceptions.py
necrophos_wsgi/http.py
necrophos_wsgi/main.py
necrophos_wsgi/response.py
necrophos_wsgi/server.py
necrophos_wsgi/utils.py
necrophos_wsgi.egg-info/PKG-INFO
necrophos_wsgi.egg-info/SOURCES.txt
necrophos_wsgi.egg-info/dependency_links.txt
necrophos_wsgi.egg-info/entry_points.txt
necrophos_wsgi.egg-info/top_level.txt