Metadata-Version: 1.0
Name: necrophos-wsgi
Version: 0.0.4
Summary: wsgi-like server based on asyncio
Home-page: https://github.com/lexdene/necrophos-wsgi
Author: Elephant Liu
Author-email: lexdene@gmail.com
License: GPLv3
Platform: UNKNOWN
